test_lab/__init__.py
test_lab/configuration.py
test_lab/log.py
test_lab/scenario.py
test_lab/server.py
test_lab/storage.py
test_lab/test_lab.py
test_lab/clients/__init__.py
test_lab/clients/adb_wrapper.py
test_lab/clients/android.py
test_lab/clients/device.py
test_lab/clients/ios.py
test_lab/clients/osx.py
test_lab/clients/subprocess_wrapper.py
test_lab-0.11.dist-info/LICENSE
test_lab-0.11.dist-info/METADATA
test_lab-0.11.dist-info/WHEEL
test_lab-0.11.dist-info/top_level.txt
test_lab-0.11.dist-info/RECORD
